<skin>
	<!-- Nemesis GreenLine Single Skin -->
	<!-- Colors (#AARRGGBB) -->
	<colors>
		<color name="dark" value="#30000000" />
		<color name="white" value="#ffffff" />
		<color name="lightgrey" value="#cccccc" />
		<color name="grey" value="#999999" />
		<color name="darkgrey" value="#4c4c4c" />
		<color name="black" value="#000000" />
		<color name="red" value="#ff0010" />
		<color name="green" value="#00cc66" />
		<color name="bright_green" value="#00ff33" />
		<color name="blue" value="#0000ff" />
		<color name="bright_blue" value="#3366ff" />
		<color name="yellow" value="#f3ca09" />
		<color name="transparent" value="#ffffffff" />
		<color name="transpWhite" value="#77ffffff" />
		<color name="transpGrey" value="#50333333" />
		<color name="transpBlack" value="#45000000" />
		<color name="transpBlue" value="#3000071e" />
		<color name="background" value="#30000000" />
		<color name="bg" value="#30000000" />
		<color name="h2" value="#acacb7" />
	</colors>
	<!-- Fonts -->
	<fonts>
		<font filename="lcd.ttf" name="LCD" scale="100" />
		<font filename="nmsbd.ttf" name="Regular" scale="95" />
		<font filename="tuxtxt.ttf" name="Console" scale="100" />
		<font filename="ae_AlMateen.ttf" name="Replacement" scale="90" is_replacement="1" />
	</fonts>
	<!-- Main screen colors (id=0 for Menu's, id=1 for LCD) -->
	<windowstyle type="skinned" id="0">
		<title offset="25,5" font="Regular;20" />
		<color name="Background" color="#30000000" />
		<color name="LabelForeground" color="#ffffff" />
		<color name="ListboxBackground" color="#30000000" />
		<color name="ListboxForeground" color="#ffffff" />
		<color name="ListboxSelectedBackground" color="#10666666" />
		<color name="ListboxSelectedForeground" color="#ffffff" />
		<color name="ListboxMarkedBackground" color="#990000" />
		<color name="ListboxMarkedForeground" color="#ffffff" />
		<color name="ListboxMarkedAndSelectedBackground" color="#ff0000" />
		<color name="ListboxMarkedAndSelectedForeground" color="#ffffff" />
		<color name="WindowTitleForeground" color="#ffffff" />
		<color name="WindowTitleBackground" color="#30000000" />
		<borderset name="bsWindow">
			<pixmap pos="bpTopLeft" filename="Nemesis.Greenline.Single/bs_tl.png" />
			<pixmap pos="bpTop" filename="Nemesis.Greenline.Single/bs_t.png" />
			<pixmap pos="bpTopRight" filename="Nemesis.Greenline.Single/bs_tr.png" />
			<pixmap pos="bpLeft" filename="Nemesis.Greenline.Single/bs_l.png" />
			<pixmap pos="bpRight" filename="Nemesis.Greenline.Single/bs_r.png" />
			<pixmap pos="bpBottomLeft" filename="Nemesis.Greenline.Single/bs_bl.png" />
			<pixmap pos="bpBottom" filename="Nemesis.Greenline.Single/bs_b.png" />
			<pixmap pos="bpBottomRight" filename="Nemesis.Greenline.Single/bs_br.png" />
		</borderset>
	</windowstyle>
	<!-- this is for LCD -->
	<windowstyle type="skinned" id="1">
		<color name="Background" color="#000000" />
		<color name="LabelForeground" color="#ffffff" />
		<color name="ListboxBackground" color="#000000" />
		<color name="ListboxForeground" color="#ffffff" />
		<color name="ListboxSelectedBackground" color="#000000" />
		<color name="ListboxSelectedForeground" color="#ffffff" />
		<color name="ListboxMarkedBackground" color="#000000" />
		<color name="ListboxMarkedForeground" color="#ffffff" />
		<color name="ListboxMarkedAndSelectedBackground" color="#000000" />
		<color name="ListboxMarkedAndSelectedForeground" color="#ffffff" />
		<color name="WindowTitleForeground" color="#ffffff" />
		<color name="WindowTitleBackground" color="#000000" />
	</windowstyle>
	<!-- Infobar -->
	<screen name="InfoBar" position="57,392" size="615,145" title="InfoBar" backgroundColor="transparent" flags="wfNoBorder">
		<ePixmap pixmap="Nemesis.Greenline.Single/ib_events.png" position="0,0" zPosition="-1" size="615,145" />
		<widget source="session.Event_Now" render="Progress" pixmap="Nemesis.Greenline.Single/progress_event.png" position="119,0" size="374,9" transparent="1" >
			<convert type="EventTime">Progress</convert>
		</widget>
		<widget source="session.CurrentService" render="Pixmap" pixmap="Nemesis.Greenline.Single/ico_subservices.png" position="16,12" size="18,18">
			<convert type="ServiceInfo">SubservicesAvailable</convert>
			<convert type="ConditionalShowHide" />
		</widget>
		<widget source="session.RecordState" render="Pixmap" pixmap="Nemesis.Greenline.Single/ico_record.png" position="16,12" size="18,18" >
			<convert type="ConditionalShowHide">Blink</convert>
		</widget>
		<widget source="session.CurrentService" render="Label" position="40,10" size="355,24" font="Regular;22" valign="top" transparent="1" backgroundColor="#444856" >
			<convert type="ServiceName">Name</convert>
		</widget>
		<widget source="global.CurrentTime" render="Label" position="400,10" size="105,24" font="Regular;22" halign="right" valign="top" backgroundColor="#444856" transparent="1" >
			<convert type="ClockToText">Format:%H:%M:%S</convert>
		</widget>
		<ePixmap pixmap="Nemesis.Greenline.Single/now.png" position="16,39" size="17,12"  alphatest="on" />
		<widget source="session.Event_Now" render="Label" position="40,35" size="60,22" font="Regular;20" backgroundColor="bg" transparent="1">
			<convert type="EventTime">StartTime</convert>
			<convert type="ClockToText">Default</convert>
		</widget>
		<widget source="session.Event_Now" render="Label" position="100,35" size="300,22" font="Regular;20" noWrap="1" backgroundColor="bg" transparent="1">
			<convert type="EventName">Name</convert>
		</widget>
		<widget source="session.Event_Now" render="Label" position="409,35" size="95,22" font="Regular;20" halign="right" backgroundColor="bg" transparent="1">
			<convert type="EventTime">Remaining</convert>
			<convert type="RemainingToText">InMinutes</convert>
		</widget>
		<widget source="session.Event_Next" render="Label" position="40,60" size="60,22" font="Regular;20" foregroundColor="h2" backgroundColor="bg" transparent="1">
			<convert type="EventTime">StartTime</convert>
			<convert type="ClockToText">Default</convert>
		</widget>
		<widget source="session.Event_Next" render="Label" position="100,60" size="300,22" font="Regular;20" noWrap="1" foregroundColor="h2" backgroundColor="bg" transparent="1">
			<convert type="EventName">Name</convert>
		</widget>
		<widget source="session.Event_Next" render="Label" position="409,60" size="95,22" font="Regular;20" halign="right" foregroundColor="h2" backgroundColor="bg" transparent="1">
			<convert type="EventTime">Duration</convert>
			<convert type="ClockToText">InMinutes</convert>
		</widget>
		<ePixmap pixmap="Nemesis.Greenline.Single/button_grey.png" position="20,89" size="12,12" alphatest="on" />
		<widget source="RecordingPossible" render="Pixmap" pixmap="Nemesis.Greenline.Single/button_red.png" position="20,89" zPosition="1" size="12,12" alphatest="on">
			<convert type="ConditionalShowHide" />
		</widget>
		<eLabel text="Record" position="40,86" size="120,18" font="Regular;16" valign="top" foregroundColor="grey" backgroundColor="#30000927" transparent="1" />
		<widget source="RecordingPossible" render="FixedLabel" text="Record" position="40,86" zPosition="1" size="120,18" font="Regular;16" valign="top" backgroundColor="#30000927" transparent="1">
			<convert type="ConditionalShowHide" />
		</widget>
		<ePixmap pixmap="Nemesis.Greenline.Single/button_grey.png" position="150,89" size="12,12" alphatest="on" />
		<widget source="session.CurrentService" render="Pixmap" pixmap="Nemesis.Greenline.Single/button_green.png" position="150,89" zPosition="1" size="12,12" alphatest="on">
			<convert type="ServiceInfo">SubservicesAvailable</convert>
			<convert type="ConditionalShowHide" />
		</widget>
		<eLabel text="Subservices" position="170,86" size="120,18" font="Regular;16" valign="top" transparent="1" foregroundColor="#50515c" backgroundColor="#30000927" />
		<widget source="session.CurrentService" render="FixedLabel" text="Subservices" position="170,86" zPosition="1" size="120,18" font="Regular;16" valign="top" backgroundColor="#30000927" transparent="1">
			<convert type="ServiceInfo">SubservicesAvailable</convert>
			<convert type="ConditionalShowHide" />
		</widget>
		<ePixmap pixmap="Nemesis.Greenline.Single/button_grey.png" position="295,89" size="12,12" alphatest="on" />
		<widget source="TimeshiftPossible" render="Pixmap" pixmap="Nemesis.Greenline.Single/button_yellow.png" position="295,89" zPosition="1" size="12,12" alphatest="on">
			<convert type="ConditionalShowHide" />
		</widget>
		<eLabel text="Timeshift" position="315,86" size="120,18" font="Regular;16" valign="top" foregroundColor="grey" backgroundColor="#30000927" transparent="1" />
		<widget source="TimeshiftPossible" render="FixedLabel" text="Timeshift" position="315,86" zPosition="1" size="120,18" font="Regular;16" valign="top" backgroundColor="#30000927" transparent="1">
			<convert type="ConditionalShowHide" />
		</widget>
		<ePixmap pixmap="Nemesis.Greenline.Single/button_grey.png" position="439,89" size="12,12" alphatest="on" />
		<widget source="ExtensionsAvailable" render="Pixmap" pixmap="Nemesis.Greenline.Single/button_blue.png" position="439,89" zPosition="1" size="12,12" alphatest="on">
			<convert type="ConditionalShowHide" />
		</widget>
		<eLabel text="Extensions" position="459,86" size="120,18" font="Regular;16" valign="top" foregroundColor="grey" backgroundColor="#30000927" transparent="1" />
		<widget source="ExtensionsAvailable" render="FixedLabel" text="Extensions" position="459,86" zPosition="1" size="120,18" font="Regular;16" valign="top" backgroundColor="#30000927" transparent="1">
			<convert type="ConditionalShowHide" />
		</widget>
		<widget source="session.FrontendInfo" render="Pixmap" pixmap="Nemesis.Greenline.Single/nim_a.png" position="537,14" size="35,19">
			<convert type="FrontendInfo">NUMBER</convert>
			<convert type="ValueRange">0,0</convert>
			<convert type="ConditionalShowHide" />
		</widget>
		<widget source="session.FrontendInfo" render="Pixmap" pixmap="Nemesis.Greenline.Single/nim_b.png" position="553,14" size="35,19">
			<convert type="FrontendInfo">NUMBER</convert>
			<convert type="ValueRange">1,1</convert>
			<convert type="ConditionalShowHide" />
		</widget>
		<widget source="session.FrontendStatus" render="Label" position="517,35" size="88,22" font="Regular;18" halign="center" backgroundColor="bg" transparent="1">
			<convert type="FrontendInfo">SNRdB</convert>
		</widget>
		<widget source="session.FrontendStatus" render="Progress" pixmap="Nemesis.Greenline.Single/progress_snr.png" position="526,57" size="73,7" transparent="1">
			<convert type="FrontendInfo">SNR</convert>
		</widget>
		<widget source="session.FrontendStatus" render="Progress" pixmap="Nemesis.Greenline.Single/progress_ber.png" position="526,70" size="73,7" transparent="1">
			<convert type="FrontendInfo">BER</convert>
		</widget>
		<widget source="session.CurrentService" render="Pixmap" pixmap="Nemesis.Greenline.Single/ico_crypt_on.png" position="406,116" size="19,12">
			<convert type="ServiceInfo">IsCrypted</convert>
			<convert type="ConditionalShowHide" />
		</widget>
		<widget source="session.CurrentService" render="Pixmap" pixmap="Nemesis.Greenline.Single/ico_txt_on.png" position="431,116" size="19,12">
			<convert type="ServiceInfo">HasTelext</convert>
			<convert type="ConditionalShowHide" />
		</widget>
		<ePixmap position="456,116" zPosition="1" size="20,12" pixmap="Nemesis.Greenline.Single/ico_dolby_off.png" />
		<widget source="session.CurrentService" render="Pixmap" pixmap="Nemesis.Greenline.Single/ico_format_on.png" position="482,116" size="19,16">
			<convert type="ServiceInfo">IsWidescreen</convert>
			<convert type="ConditionalShowHide" />
		</widget>
		<widget source="session.CurrentService" render="Pixmap" pixmap="Nemesis.Greenline.Single/ico_dolby_on.png" position="507,116" size="21,12">
			<convert type="ServiceInfo">IsMultichannel</convert>
			<convert type="ConditionalShowHide" />
		</widget>
		<widget source="session.TunerInfo" render="Pixmap" pixmap="Nemesis.Greenline.Single/ico_nim_a.png" position="534,116" size="33,13">
			<convert type="TunerInfo">TunerUseMask</convert>
			<convert type="ValueBitTest">1</convert>
			<convert type="ConditionalShowHide" />
		</widget>
		<widget source="session.TunerInfo" render="Pixmap" pixmap="Nemesis.Greenline.Single/ico_nim_b.png" position="549,116" size="31,13">
			<convert type="TunerInfo">TunerUseMask</convert>
			<convert type="ValueBitTest">2</convert>
			<convert type="ConditionalShowHide" />
		</widget>
		<ePixmap pixmap="Nemesis.Greenline.Single/dmm_logo.png" position="19,121" size="140,8" alphatest="on" />
	</screen>
	<!-- Channel selection (tv) -->
	<screen name="ChannelSelection" position="90,95" size="560,433" title="Channel Selection">
		<ePixmap pixmap="skin_default/buttons/red.png" position="0,0" size="140,40" alphatest="on" />
		<ePixmap pixmap="skin_default/buttons/green.png" position="140,0" size="140,40" alphatest="on" />
		<ePixmap pixmap="skin_default/buttons/yellow.png" position="280,0" size="140,40" alphatest="on" />
		<ePixmap pixmap="skin_default/buttons/blue.png" position="420,0" size="140,40" alphatest="on" />
		<widget name="key_red" position="0,0" zPosition="1" size="140,40" font="Regular;20" halign="center" valign="center" backgroundColor="#9f1313" transparent="1" />
		<widget name="key_green" position="140,0" zPosition="1" size="140,40" font="Regular;20" halign="center" valign="center" backgroundColor="#1f771f" transparent="1" />
		<widget name="key_yellow" position="280,0" zPosition="1" size="140,40" font="Regular;20" halign="center" valign="center" backgroundColor="#a08500" transparent="1" />
		<widget name="key_blue" position="420,0" zPosition="1" size="140,40" font="Regular;20" halign="center" valign="center" backgroundColor="#18188b" transparent="1" />
		<widget name="list" position="0,43" size="560,280" scrollbarMode="showOnDemand" />
		<ePixmap pixmap="Nemesis.Greenline.Single/separator.png" position="0,323" size="560,4" />
		<widget source="ServiceEvent" render="Label" position="10,330" size="460,20" font="Regular;19" noWrap="1">
			<convert type="EventName">Name</convert>
		</widget>
		<widget source="global.CurrentTime" render="Label" position="490,330" size="60,20" font="Regular;19" halign="right">
			<convert type="ClockToText"></convert>
		</widget>
		<widget source="ServiceEvent" render="Label" position="210,351" size="340,20" font="Regular;17" halign="right" noWrap="1">
			<convert type="ServiceName">Name</convert>
		</widget>
		<widget source="ServiceEvent" render="Label" position="10,351" zPosition="1" size="45,22" font="Regular;17" >
			<convert type="EventTime">StartTime</convert>
			<convert type="ClockToText"></convert>
		</widget>
		<widget source="ServiceEvent" render="Label" position="55,351" zPosition="1" size="65,22" font="Regular;17" >
			<convert type="EventTime">EndTime</convert>
			<convert type="ClockToText">Format:- %H:%M</convert>
		</widget>
		<widget source="ServiceEvent" render="Progress" pixmap="Nemesis.Greenline.Single/progress_volume.png" position="125,355" size="83,10" borderWidth="2" transparent="1">
			<convert type="EventTime">Progress</convert>
		</widget>
		<widget source="ServiceEvent" render="Label" position="10,371" size="540,60" font="Regular;18" foregroundColor="h2">
			<convert type="EventName">ExtendedDescription</convert>
		</widget>
	</screen>
	<!-- EPG selection (multi) -->
	<screen name="EPGSelectionMulti" position="90,95" size="560,430" title="EPG Selection">
		<ePixmap pixmap="skin_default/buttons/red.png" position="0,0" size="140,40" alphatest="on" />
		<ePixmap pixmap="skin_default/buttons/green.png" position="140,0" size="140,40" alphatest="on" />
		<ePixmap pixmap="skin_default/buttons/yellow.png" position="280,0" size="140,40" alphatest="on" />
		<ePixmap pixmap="skin_default/buttons/blue.png" position="420,0" size="140,40" alphatest="on" />
		<widget name="key_red" position="0,0" zPosition="1" size="140,40" font="Regular;20" halign="center" valign="center" backgroundColor="#9f1313" transparent="1" />
		<widget name="key_green" position="140,0" zPosition="1" size="140,40" font="Regular;20" halign="center" valign="center" backgroundColor="#1f771f" transparent="1" />
		<widget name="key_yellow" position="280,0" zPosition="1" size="140,40" font="Regular;20" halign="center" valign="center" backgroundColor="#a08500" transparent="1" />
		<widget name="key_blue" position="420,0" zPosition="1" size="140,40" font="Regular;20" halign="center" valign="center" backgroundColor="#18188b" transparent="1" />
		<widget name="now_button" position="1,1" size="1,1" />
		<widget name="next_button" position="1,1" size="1,1" />
		<widget name="more_button" position="1,1" size="1,1" />
		<widget name="now_button_sel" position="5,50" zPosition="2" size="320,25" pixmap="Nemesis.Greenline.Single/epg_now.png" alphatest="on" />
		<widget name="next_button_sel" position="5,50" zPosition="2" size="320,25" pixmap="Nemesis.Greenline.Single/epg_next.png" alphatest="on" />
		<widget name="more_button_sel" position="5,50" zPosition="2" size="320,25" pixmap="Nemesis.Greenline.Single/epg_more.png" alphatest="on" />
		<widget name="now_text" text="NOW" zPosition="3" position="5,50" size="108,22" transparent="1" halign="center" valign="center" font="Regular;16" />
		<widget name="next_text" text="NEXT" zPosition="3" position="111,50" size="108,22" transparent="1" halign="center" valign="center" font="Regular;16" />
		<widget name="more_text" text="MORE" zPosition="3" position="216,50" size="108,22" transparent="1" halign="center" valign="center" font="Regular;16" />
		<widget name="date" position="410,35" size="140,45" valign="center" halign="right" font="Regular;18" />
		<widget name="list" position="11,75" size="540,350" scrollbarMode="showOnDemand" />
		<ePixmap pixmap="Nemesis.Greenline.Single/epg_frame.png" position="5,70" zPosition="1" size="551,361" alphatest="on" />
	</screen>
	<!-- Graphical Multi EPG -->
	<screen name="GraphMultiEPG" position="90,95" size="560,435" title="Electronic Program Guide">
		<ePixmap pixmap="skin_default/buttons/red.png" position="0,0" size="140,40" alphatest="on" />
		<ePixmap pixmap="skin_default/buttons/green.png" position="140,0" size="140,40" alphatest="on" />
		<ePixmap pixmap="skin_default/buttons/yellow.png" position="280,0" size="140,40" alphatest="on" />
		<ePixmap pixmap="skin_default/buttons/blue.png" position="420,0" size="140,40" alphatest="on" />
		<widget name="key_red" position="0,0" zPosition="1" size="140,40" font="Regular;20" halign="center" valign="center" backgroundColor="#9f1313" transparent="1" />
		<widget name="key_green" position="140,0" zPosition="1" size="140,40" font="Regular;20" halign="center" valign="center" backgroundColor="#1f771f" transparent="1" />
		<widget name="timeline_text" position="0,41" size="560,20" />
		<widget name="list" position="0,65" size="560,270" EntryBorderColor="#000000" EntryBackgroundColor="#10333333" EntryBackgroundColorSelected="#20666666" scrollbarMode="showOnDemand" />
		<widget name="timeline0" position="0,65" zPosition="1" size="1,270" pixmap="skin_default/timeline.png" />
		<widget name="timeline1" position="0,65" zPosition="1" size="1,270" pixmap="skin_default/timeline.png" />
		<widget name="timeline2" position="0,65" zPosition="1" size="1,270" pixmap="skin_default/timeline.png" />
		<widget name="timeline3" position="0,65" zPosition="1" size="1,270" pixmap="skin_default/timeline.png" />
		<widget name="timeline4" position="0,65" zPosition="1" size="1,270" pixmap="skin_default/timeline.png" />
		<widget name="timeline5" position="0,65" zPosition="1" size="1,270" pixmap="skin_default/timeline.png" />
		<widget name="timeline_now" position="0,64" zPosition="2" size="19,273" pixmap="skin_default/timeline-now.png" alphatest="on" />
		<ePixmap pixmap="Nemesis.Greenline.Single/border_multiepg.png" position="0,42" zPosition="1" size="560,393" transparent="1" alphatest="on" />
		<widget source="Event" render="Label" position="10,337" zPosition="1" size="460,20" font="Regular;19" noWrap="1">
			<convert type="EventName">Name</convert>
		</widget>
		<ePixmap pixmap="skin_default/icons/clock.png" position="478,339" zPosition="1" size="14,14" alphatest="on" />
		<widget source="global.CurrentTime" render="Label" position="495,337" zPosition="1" size="55,20" font="Regular;19" halign="right">
			<convert type="ClockToText"></convert>
		</widget>
		<widget source="Event" render="Label" position="10,357" zPosition="1" size="50,22" font="Regular;18">
			<convert type="EventTime">StartTime</convert>
			<convert type="ClockToText"></convert>
		</widget>
		<widget source="Event" render="Label" position="60,357" zPosition="1" size="70,22" font="Regular;18">
			<convert type="EventTime">EndTime</convert>
			<convert type="ClockToText">Format:- %H:%M</convert>
		</widget>
		<widget source="Event" render="Progress" position="125,360" zPosition="1" pixmap="skin_default/progress_medium.png" size="65,11" borderWidth="2" borderColor="#cccccc">
			<convert type="EventTime">Progress</convert>
		</widget>
		<widget source="Event" render="Label" position="200,357" zPosition="1" size="350,20" font="Regular;18" noWrap="1">
			<convert type="EventTime">StartTime</convert>
			<convert type="ClockToText">Format:(%A)</convert>
		</widget>
		<widget source="Event" render="Label" position="10,377" zPosition="1" size="540,53" font="Regular;16" foregroundColor="#cccccc">
			<convert type="EventName">ExtendedDescription</convert>
		</widget>
	</screen>
	<!-- Mediaplayer -->
	<screen name="MediaPlayer" position="40,55" size="640,476" title="MediaPlayer" backgroundColor="transparent" flags="wfNoBorder">
		<ePixmap pixmap="Nemesis.Greenline.Single/mediaplayer.png" position="0,0" zPosition="-1" size="640,476" />
		<ePixmap pixmap="Nemesis.Greenline.Single/mp_buttons.png" position="460,446" size="138,13" alphatest="on" />
		<widget name="artisttext" position="25,15" size="65,17" font="Regular;16" valign="top" foregroundColor="h2" backgroundColor="#25293d" transparent="1" />
		<widget name="artist" position="90,15" size="385,17" font="Regular;16" valign="top" backgroundColor="#25293d" transparent="1" />
		<widget name="albumtext" position="25,34" size="65,17" font="Regular;16" valign="top" foregroundColor="h2" backgroundColor="#25293d" transparent="1" />
		<widget name="album" position="90,34" size="385,17" font="Regular;16" valign="top" backgroundColor="#25293d" transparent="1" />
		<widget name="yeartext" position="25,54" size="65,17" font="Regular;16" valign="top" foregroundColor="h2" backgroundColor="#25293d" transparent="1" />
		<widget name="year" position="90,54" size="385,17" font="Regular;16" valign="top" backgroundColor="#25293d" transparent="1" />
		<widget name="genretext" position="25,74" size="65,17" font="Regular;16" valign="top" foregroundColor="h2" backgroundColor="#25293d" transparent="1" />
		<widget name="genre" position="90,74" size="385,17" font="Regular;16" valign="top" backgroundColor="#25293d" transparent="1" />
		<eLabel text="Now Playing" position="25,101" size="385,14" font="Regular;12" foregroundColor="#ffcc00" transparent="1" />
		<widget name="title" position="25,114" size="385,18" font="Regular;16" valign="top" transparent="1" />
		<widget name="coverArt" pixmap="Nemesis.Greenline.Single/no_coverArt.png" position="504,15" size="116,116" alphatest="on" />
		<widget name="filelist" position="41,143" size="578,115" scrollbarMode="showOnDemand" />
		<widget name="playlist" position="41,270" size="578,154" scrollbarMode="showOnDemand" selectionDisabled="1" />
		<widget name="PositionGauge" pointer="Nemesis.Greenline.Single/position_pointer.png:516,0" position="12,449" size="320,10" transparent="1" />
		<ePixmap pixmap="Nemesis.Greenline.Single/position_overlay_l.png" position="8,447" zPosition="1" size="7,15" alphatest="on" />
		<ePixmap pixmap="Nemesis.Greenline.Single/position_overlay_r.png" position="328,447" zPosition="1" size="7,15" alphatest="on" />
		<widget name="currenttext" position="1,1" size="1,1" />
		<widget name="titletext" position="1,1" size="1,1" />
	</screen>
	<!-- Main menu -->
	<screen name="menu_mainmenu" position="170,150" size="380,285" title="Main menu">
		<widget source="title" render="Label" position="170,10" size="200,35" font="Regular;23" />
		<widget source="menu" render="Listbox" position="170,55" size="200,225" scrollbarMode="showOnDemand">
			<convert type="StringList" />
		</widget>
		<widget source="menu" render="Pixmap" pixmap="skin_default/menu/dvd_player.png" position="20,20" size="128,128" alphatest="on">
			<convert type="MenuEntryCompare">dvd_player</convert>
			<convert type="ConditionalShowHide" />
		</widget>
		<widget source="menu" render="Pixmap" pixmap="skin_default/menu/subtitles.png" position="20,20" size="128,128" alphatest="on">
			<convert type="MenuEntryCompare">subtitle_selection</convert>
			<convert type="ConditionalShowHide"/>
		</widget>
		<widget source="menu" render="Pixmap" pixmap="skin_default/menu/media_player.png" position="20,20" size="128,128" alphatest="on">
			<convert type="MenuEntryCompare">media_player</convert>
			<convert type="ConditionalShowHide" />
		</widget>
		<widget source="menu" render="Pixmap" pixmap="skin_default/menu/timer.png" position="20,20" size="128,128" alphatest="on">
			<convert type="MenuEntryCompare">timer_edit</convert>
			<convert type="ConditionalShowHide" />
		</widget>
		<widget source="menu" render="Pixmap" pixmap="skin_default/menu/scart.png" position="20,20" size="128,128" alphatest="on">
			<convert type="MenuEntryCompare">scart_switch</convert>
			<convert type="ConditionalShowHide" />
		</widget>
		<widget source="menu" render="Pixmap" pixmap="skin_default/menu/information.png" position="20,20" size="128,128" alphatest="on">
			<convert type="MenuEntryCompare">info_screen</convert>
			<convert type="ConditionalShowHide" />
		</widget>
		<widget source="menu" render="Pixmap" pixmap="skin_default/menu/plugins.png" position="20,20" size="128,128" alphatest="on">
			<convert type="MenuEntryCompare">plugin_selection</convert>
			<convert type="ConditionalShowHide" />
		</widget>
		<widget source="menu" render="Pixmap" pixmap="skin_default/menu/setup.png" position="20,20" size="128,128" alphatest="on">
			<convert type="MenuEntryCompare">setup_selection</convert>
			<convert type="ConditionalShowHide" />
		</widget>
		<widget source="menu" render="Pixmap" pixmap="skin_default/menu/shutdown.png" position="20,20" size="128,128" alphatest="on">
			<convert type="MenuEntryCompare">standby_restart_list</convert>
			<convert type="ConditionalShowHide" />
		</widget>
	</screen>
	<!-- Movieplayer -->
	<screen name="MoviePlayer" position="45,465" size="640,90" title="MoviePlayer" backgroundColor="transparent" flags="wfNoBorder">
		<ePixmap pixmap="Nemesis.Greenline.Single/movieplayer.png" position="0,0" zPosition="-1" size="640,90" />
		<widget source="session.CurrentService" render="PositionGauge" pointer="Nemesis.Greenline.Single/position_pointer.png:516,0" position="19,64" size="305,10" transparent="1">
			<convert type="ServicePosition">Gauge</convert>
		</widget>
		<ePixmap pixmap="Nemesis.Greenline.Single/position_overlay_l.png" position="14,62" zPosition="1" size="7,15" alphatest="on" />
		<ePixmap pixmap="Nemesis.Greenline.Single/position_overlay_r.png" position="317,62" zPosition="1" size="7,15" alphatest="on" />
		<widget source="session.CurrentService" render="Label" position="20,12" size="510,38" font="Regular;20" valign="center" noWrap="1" backgroundColor="bg" transparent="1">
			<convert type="ServiceName">Name</convert>
		</widget>
		<widget source="session.CurrentService" render="Label" position="435,12" size="100,38" font="Regular;20" halign="right" valign="center" backgroundColor="bg" transparent="1">
			<convert type="ServicePosition">Position</convert>
		</widget>
		<eLabel position="540,12" size="10,38" text="/" font="Regular;20" halign="center" valign="center" backgroundColor="bg" transparent="1" />
		<widget source="session.CurrentService" render="Label" position="555,12" size="100,38" font="Regular;20" halign="left" valign="center" backgroundColor="bg" transparent="1">
			<convert type="ServicePosition">Length</convert>
		</widget>
		<ePixmap pixmap="Nemesis.Greenline.Single/mp_buttons.png" position="449,62" size="138,13" alphatest="on" />
	</screen>
	<!-- Movieselection -->
	<screen name="MovieSelection" position="90,83" size="560,445" title="Select a movie">
		<ePixmap pixmap="skin_default/buttons/red.png" position="0,0" size="140,40" alphatest="on" />
		<ePixmap pixmap="skin_default/buttons/green.png" position="140,0" size="140,40" alphatest="on" />
		<ePixmap pixmap="skin_default/buttons/yellow.png" position="280,0" size="140,40" alphatest="on" />
		<ePixmap pixmap="skin_default/buttons/blue.png" position="420,0" size="140,40" alphatest="on" />
		<widget name="key_red" position="0,0" zPosition="1" size="140,40" font="Regular;20" halign="center" valign="center" backgroundColor="#9f1313" transparent="1" />
		<widget name="key_green" position="140,0" zPosition="1" size="140,40" font="Regular;20" halign="center" valign="center" backgroundColor="#1f771f" transparent="1" />
		<widget name="key_yellow" position="280,0" zPosition="1" size="140,40" font="Regular;20" halign="center" valign="center" backgroundColor="#a08500" transparent="1" />
		<widget name="key_blue" position="420,0" zPosition="1" size="140,40" font="Regular;20" halign="center" valign="center" backgroundColor="#18188b" transparent="1" />
		<widget name="waitingtext" position="0,45" size="560,395" zPosition="4" font="Regular;22" halign="center" valign="center" />
		<widget name="list" position="0,40" size="560,375" scrollbarMode="showOnDemand" />
		<widget name="DescriptionBorder" pixmap="Nemesis.Greenline.Single/border_eventinfo.png" position="0,316" size="560,103" alphatest="on" />
		<widget source="Service" render="Label" position="5,318" size="480,35" font="Regular;17" foregroundColor="#cccccc">
			<convert type="MovieInfo">ShortDescription</convert>
		</widget>
		<widget source="Service" render="Label" position="495,318" size="60,22" font="Regular;17" halign="right">
			<convert type="ServiceTime">Duration</convert>
			<convert type="ClockToText">AsLength</convert>
		</widget>
		<widget source="Service" render="Label" position="380,337" size="175,22" font="Regular;17" halign="right">
			<convert type="MovieInfo">RecordServiceName</convert>
		</widget>
		<widget source="Service" render="Label" position="5,357" size="550,58" font="Regular;19">
			<convert type="EventName">ExtendedDescription</convert>
		</widget>
		<widget name="freeDiskSpace" position="10,425" size="540,20" font="Regular;19" halign="right" valign="center" />
	</screen>
	<!-- Volume -->
	<screen name="Volume" position="485,60" zPosition="1" size="160,19" title="Volume" flags="wfNoBorder">
		<ePixmap position="0,0" size="164,19" pixmap="Nemesis.Greenline.Single/volumeslider.png" />
		<widget name="Volume" pixmap="Nemesis.Greenline.Single/progress_volume.png" position="32,4" zPosition="1" size="120,10" backgroundColor="#0b1028" />
	</screen>
</skin>
